pushbot/__init__.py
pushbot/push_bot.py
pushbot/repush_bot.py
pushbot/setup.py
pushbot-0.1.1.dist-info/METADATA
pushbot-0.1.1.dist-info/WHEEL
pushbot-0.1.1.dist-info/top_level.txt
pushbot-0.1.1.dist-info/RECORD
