Metadata-Version: 2.1
Name: pushbot
Version: 0.1.1
Summary: A Python package to create repo and push code on Github
Home-page: https://github.com/sleepingcat4/push-bot
Author: TAWSIF AHMED
Author-email: sleeping4cat@outlook.com
License: MIT
